swtools/__init__.py
swtools/__main__.py
swtools/cli.py
swtools/constants.py
swtools/database.py
swtools/functions.py
swtools/reports.py
swtools/swling.py
swtools/swlookup.py
swtools/swupdate.py
swtools/data/shortwave.sqlite3
swtools-1.1.0.dist-info/AUTHORS.rst
swtools-1.1.0.dist-info/LICENSE
swtools-1.1.0.dist-info/METADATA
swtools-1.1.0.dist-info/WHEEL
swtools-1.1.0.dist-info/entry_points.txt
swtools-1.1.0.dist-info/top_level.txt
swtools-1.1.0.dist-info/RECORD
