Metadata-Version: 2.1
Name: swtools
Version: 1.1.0
Summary: Shortwave CLI tools for SWLing and DXing!
Home-page: https://gitlab.com/pparise/swtools
Author: Philippe Pariseau
Author-email: phil.pariseau@gmail.com
License: MIT license
Keywords: swtools
Platform: UNKNOWN
Classifier: Development Status :: 3 - Alpha
Classifier: Intended Audience :: Developers
Classifier: License :: OSI Approved :: MIT License
Classifier: Natural Language :: English
Classifier: Programming Language :: Python :: 3
Classifier: Programming Language :: Python :: 3.5
Classifier: Programming Language :: Python :: 3.6
Classifier: Programming Language :: Python :: 3.7
Classifier: Programming Language :: Python :: 3.8
Requires-Python: >=3
Requires-Dist: beautifultable
Requires-Dist: pandas
Requires-Dist: tzlocal
